refresh_legacy_aws_sso_profile-1.0.0.dist-info/METADATA
refresh_legacy_aws_sso_profile-1.0.0.dist-info/WHEEL
refresh_legacy_aws_sso_profile-1.0.0.dist-info/entry_points.txt
refresh_legacy_aws_sso_profile-1.0.0.dist-info/licenses/LICENSE
refresh_legacy_aws_sso_profile/__init__.py
refresh_legacy_aws_sso_profile/cli/__init__.py
refresh_legacy_aws_sso_profile/cli/refresh_legacy_sso/__init__.py
refresh_legacy_aws_sso_profile/cli/refresh_legacy_sso/__main__.py
refresh_legacy_aws_sso_profile/cli/refresh_legacy_sso/impl.py
refresh_legacy_aws_sso_profile/refresh.py
refresh_legacy_aws_sso_profile/version.py
refresh_legacy_aws_sso_profile-1.0.0.dist-info/RECORD
