Metadata-Version: 2.1
Name: refresh-legacy-aws-sso-profile
Version: 1.0.0
Summary: A tool to create/refresh a backwards-compatible AWS profile with temporary credentials from a new-style AWS SSO profile.
Keywords: AWS credentials SSO login token authentication auth
Home-page: https://github.com/mckelvie-org/py-refresh-legacy-aws-sso-profile
Author-Email: Sam McKelvie <dev@mckelvie.org>
License: MIT
Project-URL: Homepage, https://github.com/mckelvie-org/py-refresh-legacy-aws-sso-profile
Project-URL: Repository, https://github.com/mckelvie-org/py-refresh-legacy-aws-sso-profile.git
Requires-Python: >=3.10
Requires-Dist: roundtripini>=0.4.0
Requires-Dist: boto3>=1.34.63
